{
  "usingComponents": {
    "i-avatar": "/static/iview/avatar/index",
    "i-panel": "/static/iview/panel/index",
    "i-cell-group": "/static/iview/cell-group/index",
    "i-cell": "/static/iview/cell/index",
    "i-row": "/static/iview/row/index",
    "i-col": "/static/iview/col/index",
    "i-toast": "/static/iview/toast/index",
    "i-swipeout": "/static/iview/swipeout/index",
    "i-icon": "/static/iview/icon/index",
    "i-modal": "/static/iview/modal/index",
    "i-divider": "/static/iview/divider/index"
  }
}